whatsappy/__init__.py
whatsappy/whatsapp.py
whatsappy/chat/__init__.py
whatsappy/chat/chat.py
whatsappy/chat/conversation.py
whatsappy/chat/group.py
whatsappy/messages/__init__.py
whatsappy/messages/audio.py
whatsappy/messages/contact.py
whatsappy/messages/document.py
whatsappy/messages/image.py
whatsappy/messages/location.py
whatsappy/messages/message.py
whatsappy/messages/sticker.py
whatsappy/messages/unread_message.py
whatsappy/messages/video.py
whatsappy/util/__init__.py
whatsappy/util/exceptions.py
whatsappy/util/me.py
whatsappy/util/other.py
whatsappy/util/selectors.py
whatsappy/util/selenium.py
whatsappy_py-4.2.1.dist-info/LICENSE
whatsappy_py-4.2.1.dist-info/METADATA
whatsappy_py-4.2.1.dist-info/WHEEL
whatsappy_py-4.2.1.dist-info/top_level.txt
whatsappy_py-4.2.1.dist-info/RECORD
