Metadata-Version: 2.1
Name: whatsappy-py
Version: 4.2.1
Summary: Whatsappy is a Python library for interacting with WhatsApp Web using Selenium. With this library, you can automate WhatsApp tasks such as sending messages, creating groups, and more.
Home-page: https://github.com/italoseara/whatsappy
Author: Italo Seara
Author-email: italo.sseara@gmail.com
Classifier: Programming Language :: Python :: 3.11
Classifier: License :: OSI Approved :: MIT License
Classifier: Operating System :: OS Independent
Classifier: Topic :: Communications :: Chat
Classifier: Topic :: Home Automation
Classifier: Topic :: Internet
Requires-Python: >=3.11
License-File: LICENSE
Requires-Dist: selenium >=4.11.2
Requires-Dist: qrcode >=7.4.2
Requires-Dist: pillow >=9.5.0
Requires-Dist: beautifulsoup4 >=4.12.2
Requires-Dist: datefinder >=0.7.3
